magic_wand/__init__.py
magic_wand/compressed_storage_format.py
magic_wand/functional.py
magic_wand/marlin.py
magic_wand/nm_ops.so
magic_wand/ops.py
magic_wand/quant.py
magic_wand/quant_utils.py
magic_wand/semi_structured.py
magic_wand/sparse_tensor.py
magic_wand/utils.py
magic_wand/nn/__init__.py
magic_wand/nn/modules.py
magic_wand/torch/__init__.py
magic_wand/torch/sparse_model.py
nm_magic_wand_nightly-0.2.2.20240522.dist-info/LICENSE
nm_magic_wand_nightly-0.2.2.20240522.dist-info/METADATA
nm_magic_wand_nightly-0.2.2.20240522.dist-info/WHEEL
nm_magic_wand_nightly-0.2.2.20240522.dist-info/top_level.txt
nm_magic_wand_nightly-0.2.2.20240522.dist-info/RECORD
